[{"marker":[0],"components":[{"x":63,"y":35}]},{"marker":[1],"components":[{"x":45,"y":6}]},{"marker":[2],"components":[{"x":42,"y":8}]},{"marker":[3],"components":[{"x":11,"y":27}]},{"marker":[5],"components":[null]}][{"marker":[0],"components":[{"glyph":64,"fg":{"r":1.0,"g":1.0,"b":0.0},"bg":{"r":0.0,"g":0.0,"b":0.0},"render_order":0}]},{"marker":[1],"components":[{"glyph":41,"fg":{"r":1.0,"g":0.64705884,"b":0.0},"bg":{"r":0.0,"g":0.0,"b":0.0},"render_order":2}]},{"marker":[2],"components":[{"glyph":41,"fg":{"r":0.0,"g":1.0,"b":1.0},"bg":{"r":0.0,"g":0.0,"b":0.0},"render_order":2}]},{"marker":[3],"components":[{"glyph":41,"fg":{"r":0.0,"g":1.0,"b":1.0},"bg":{"r":0.0,"g":0.0,"b":0.0},"render_order":2}]},{"marker":[5],"components":[null]}][{"marker":[0],"components":[{}]},{"marker":[1],"components":[null]},{"marker":[2],"components":[null]},{"marker":[3],"components":[null]},{"marker":[5],"components":[null]}][{"marker":[0],"components":[{"visible_tiles":[{"x":67,"y":31},{"x":61,"y":29},{"x":63,"y":36},{"x":68,"y":36},{"x":59,"y":30},{"x":68,"y":30},{"x":60,"y":35},{"x":67,"y":28},{"x":63,"y":31},{"x":69,"y":32},{"x":64,"y":31},{"x":65,"y":34},{"x":62,"y":33},{"x":69,"y":35},{"x":59,"y":35},{"x":60,"y":29},{"x":63,"y":35},{"x":60,"y":30},{"x":61,"y":32},{"x":66,"y":28},{"x":61,"y":33},{"x":65,"y":33},{"x":67,"y":30},{"x":68,"y":31},{"x":59,"y":33},{"x":67,"y":32},{"x":60,"y":33},{"x":67,"y":34},{"x":61,"y":31},{"x":65,"y":31},{"x":62,"y":35},{"x":66,"y":34},{"x":65,"y":29},{"x":62,"y":32},{"x":66,"y":27},{"x":64,"y":35},{"x":63,"y":27},{"x":64,"y":29},{"x":64,"y":28},{"x":65,"y":35},{"x":62,"y":31},{"x":67,"y":33},{"x":61,"y":35},{"x":62,"y":36},{"x":66,"y":32},{"x":60,"y":36},{"x":66,"y":29},{"x":63,"y":28},{"x":64,"y":33},{"x":61,"y":28},{"x":64,"y":30},{"x":59,"y":31},{"x":64,"y":32},{"x":63,"y":29},{"x":68,"y":28},{"x":61,"y":34},{"x":61,"y":30},{"x":68,"y":32},{"x":69,"y":31},{"x":63,"y":34},{"x":68,"y":34},{"x":69,"y":30},{"x":65,"y":30},{"x":65,"y":32},{"x":60,"y":32},{"x":64,"y":34},{"x":68,"y":33},{"x":59,"y":32},{"x":64,"y":36},{"x":60,"y":28},{"x":59,"y":29},{"x":68,"y":29},{"x":62,"y":27},{"x":62,"y":34},{"x":60,"y":27},{"x":67,"y":35},{"x":67,"y":36},{"x":66,"y":33},{"x":69,"y":33},{"x":60,"y":31},{"x":62,"y":30},{"x":68,"y":35},{"x":63,"y":30},{"x":59,"y":36},{"x":62,"y":28},{"x":69,"y":29},{"x":65,"y":28},{"x":66,"y":35},{"x":69,"y":34},{"x":61,"y":27},{"x":67,"y":29},{"x":66,"y":30},{"x":65,"y":27},{"x":66,"y":36},{"x":62,"y":29},{"x":63,"y":32},{"x":60,"y":34},{"x":69,"y":36},{"x":59,"y":34},{"x":63,"y":33},{"x":65,"y":36},{"x":64,"y":27},{"x":66,"y":31},{"x":61,"y":36},{"x":59,"y":28}],"range":8,"dirty":false}]},{"marker":[1],"components":[null]},{"marker":[2],"components":[null]},{"marker":[3],"components":[null]},{"marker":[5],"components":[null]}][{"marker":[0],"components":[null]},{"marker":[1],"components":[null]},{"marker":[2],"components":[null]},{"marker":[3],"components":[null]},{"marker":[5],"components":[null]}][{"marker":[0],"components":[{"name":"Player"}]},{"marker":[1],"components":[{"name":"Fireball Scroll"}]},{"marker":[2],"components":[{"name":"Magic Missile Scroll"}]},{"marker":[3],"components":[{"name":"Magic Missile Scroll"}]},{"marker":[5],"components":[null]}][{"marker":[0],"components":[null]},{"marker":[1],"components":[null]},{"marker":[2],"components":[null]},{"marker":[3],"components":[null]},{"marker":[5],"components":[null]}][{"marker":[0],"components":[{"max_hp":30,"hp":30,"defense":2,"power":5}]},{"marker":[1],"components":[null]},{"marker":[2],"components":[null]},{"marker":[3],"components":[null]},{"marker":[5],"components":[null]}][{"marker":[0],"components":[null]},{"marker":[1],"components":[null]},{"marker":[2],"components":[null]},{"marker":[3],"components":[null]},{"marker":[5],"components":[null]}][{"marker":[0],"components":[null]},{"marker":[1],"components":[null]},{"marker":[2],"components":[null]},{"marker":[3],"components":[null]},{"marker":[5],"components":[null]}][{"marker":[0],"components":[null]},{"marker":[1],"components":[{}]},{"marker":[2],"components":[{}]},{"marker":[3],"components":[{}]},{"marker":[5],"components":[null]}][{"marker":[0],"components":[null]},{"marker":[1],"components":[{}]},{"marker":[2],"components":[{}]},{"marker":[3],"components":[{}]},{"marker":[5],"components":[null]}][{"marker":[0],"components":[null]},{"marker":[1],"components":[{"range":6}]},{"marker":[2],"components":[{"range":6}]},{"marker":[3],"components":[{"range":6}]},{"marker":[5],"components":[null]}][{"marker":[0],"components":[null]},{"marker":[1],"components":[{"damage":20}]},{"marker":[2],"components":[{"damage":20}]},{"marker":[3],"components":[{"damage":20}]},{"marker":[5],"components":[null]}][{"marker":[0],"components":[null]},{"marker":[1],"components":[{"radius":3}]},{"marker":[2],"components":[null]},{"marker":[3],"components":[null]},{"marker":[5],"components":[null]}][{"marker":[0],"components":[null]},{"marker":[1],"components":[null]},{"marker":[2],"components":[null]},{"marker":[3],"components":[null]},{"marker":[5],"components":[null]}][{"marker":[0],"components":[null]},{"marker":[1],"components":[null]},{"marker":[2],"components":[null]},{"marker":[3],"components":[null]},{"marker":[5],"components":[null]}][{"marker":[0],"components":[null]},{"marker":[1],"components":[null]},{"marker":[2],"components":[null]},{"marker":[3],"components":[null]},{"marker":[5],"components":[null]}][{"marker":[0],"components":[null]},{"marker":[1],"components":[null]},{"marker":[2],"components":[null]},{"marker":[3],"components":[null]},{"marker":[5],"components":[null]}][{"marker":[0],"components":[null]},{"marker":[1],"components":[null]},{"marker":[2],"components":[null]},{"marker":[3],"components":[null]},{"marker":[5],"components":[null]}][{"marker":[0],"components":[null]},{"marker":[1],"components":[null]},{"marker":[2],"components":[null]},{"marker":[3],"components":[null]},{"marker":[5],"components":[null]}][{"marker":[0],"components":[null]},{"marker":[1],"components":[null]},{"marker":[2],"components":[null]},{"marker":[3],"components":[null]},{"marker":[5],"components":[{"map":{"tiles":["Wall","Wall","Wall","Wall","Wall","Wall","Wall","Wall","Wall","Wall","Wall","Wall","Wall","Wall","Wall","Wall","Wall","Wall","Wall","Wall","Wall","Wall","Wall","Wall","Wall","Wall","Wall","Wall","Wall","Wall","Wall","Wall","Wall","Wall","Wall","Wall","Wall","Wall","Wall","Wall","Wall","Wall","Wall","Wall","Wall","Wall","Wall","Wall","Wall","Wall","Wall","Wall","Wall","Wall","Wall","Wall","Wall","Wall","Wall","Wall","Wall","Wall","Wall","Wall","Wall","Wall","Wall","Wall","Wall","Wall","Wall","Wall","Wall","Wall","Wall","Wall","Wall","Wall","Wall","Wall","Wall","Wall","Wall","Wall","Wall","Wall","Wall","Wall","Wall","Wall","Wall","Wall","Wall","Wall","Wall","Wall","Wall","Wall","Wall","Wall","Wall","Wall","Wall","Wall","Wall","Wall","Wall","Wall","Wall","Wall","Wall","Wall","Wall","Wall","Wall","Wall","Wall","Wall","Wall","Wall","Wall","Wall","Wall","Wall","Wall","Wall","Wall","Wall","Wall","Wall","Wall","Wall","Wall","Wall","Wall","Wall","Wall","Wall","Wall","Wall","Wall","Wall","Wall","Wall","Wall","Wall","Wall","Wall","Wall","Wall","Wall","Wall","Wall","Wall","Wall","Wall","Wall","Wall","Wall","Wall","Wall","Wall","Wall","Wall","Wall","Wall","Wall","Wall","Wall","Wall","Wall","Floor","Floor","Floor","Floor","Floor","Floor","Wall","Wall","Wall","Wall","Wall","Wall","Wall","Wall","Wall","Wall","Wall","Wall","Wall","Wall","Wall","Wall","Wall","Wall","Wall","Wall","Wall","Wall","Wall","Wall","Wall","Wall","Wall","Wall","Wall","Wall","Wall","Wall","Wall","Wall","Wall","Wall","Wall","Wall","Wall","Wall","Wall","Wall","Wall","Wall","Wall","Wall","Wall","Wall","Wall","Wall","Wall","Wall","Wall","Wall","Wall","Wall","Wall","Wall","Wall","Wall","Wall","Wall","Wall","Wall","Wall","Wall","Wall","Wall","Wall","Wall","Wall","Wall","Wall","Wall","Floor","Floor","Floor","Floor","Floor","Floor","Wall","Wall","Wall","Wall","Wall","Wall","Wall","Wall","Wall","Wall","Wall","Wall","Wall","Wall","Wall","Wall","Wall","Wall","Wall","Wall","Wall","Wall","Wall","Floor","Floor","Floor","Floor","Floor","Floor","Floor","Floor","Floor","Wall","Wall","Wall","Wall","Wall","Wall","Wall","Wall","Wall","Wall","Wall","Wall","Wall","Wall","Wall","Wall","Wall","Wall","Wall","Wall","Wall","Wall","Wall","Wall","Wall","Wall","Wall","Wall","Wall","Wall","Wall","Wall","Wall","Wall","Wall","Wall","Wall","Wall","Wall","Wall","Wall","Wall","Floor","Floor","Floor","Floor","Floor","Floor","Wall","Wall","Wall","Wall","Wall","Wall","Wall","Wall","Wall","Wall","Wall","Wall","Wall","Wall","Wall","Wall","Wall","Wall","Wall","Wall","Wall","Wall","Wall","Floor","Floor","Floor","Floor","Floor","Floor","Floor","Floor","Floor","Wall","Wall","Wall","Wall","Wall","Wall","Wall","Wall","Wall","Wall","Wall","Wall","Wall","Wall","Wall","Wall","Wall","Wall","Wall","Wall","Wall","Wall","Wall","Wall","Wall","Wall","Wall","Wall","Wall","Wall","Wall","Wall","Wall","Wall","Wall","Wall","Wall","Wall","Wall","Wall","Wall","Wall","Floor","Floor","Floor","Floor","Floor","Floor","Wall","Wall","Wall","Wall","Wall","Wall","Wall","Wall","Wall","Wall","Wall","Wall","Wall","Wall","Wall","Wall","Wall","Wall","Wall","Wall","Wall","Wall","Wall","Floor","Floor","Floor","Floor","Floor","Floor","Floor","Floor","Floor","Wall","Wall","Wall","Wall","Wall","Wall","Wall","Wall","Wall","Wall","Wall","Wall","Wall","Wall","Wall","Floor","Floor","Floor","Floor","Floor","Floor","Wall","Wall","Wall","Wall","Wall","Wall","Wall","Wall","Wall","Wall","Wall","Wall","Wall","Wall","Wall","Wall","Wall","Wall","Wall","Wall","Wall","Floor","Floor","Floor","Floor","Floor","Floor","Wall","Wall","Wall","Wall","Wall","Wall","Wall","Wall","Wall","Wall","Wall","Wall","Wall","Wall","Wall","Wall","Wall","Wall","Wall","Wall","Wall","Wall","Wall","Floor","Floor","Floor","Floor","Floor","Floor","Floor","Floor","Floor","Wall","Wall","Wall","Wall","Wall","Wall","Wall","Wall","Wall","Wall","Wall","Wall","Wall","Wall","Wall","Floor","Floor","Floor","Floor","Floor","Floor","Wall","Wall","Wall","Wall","Wall","Wall","Wall","Wall","Wall","Wall","Wall","Wall","Wall","Wall","Wall","Wall","Wall","Wall","Wall","Wall","Wall","Floor","Floor","Floor","Floor","Floor","Floor","Wall","Wall","Floor","Floor","Floor","Floor","Floor","Floor","Floor","Floor","Floor","Floor","Floor","Floor","Floor","Floor","Floor","Floor","Floor","Floor","Floor","Floor","Floor","Floor","Floor","Floor","Floor","Floor","Floor","Floor","Floor","Floor","Floor","Floor","Floor","Floor","Floor","Floor","Floor","Floor","Floor","Floor","Floor","Floor","Floor","Floor","Floor","Floor","Floor","Floor","Floor","Floor","Floor","Wall","Wall","Wall","Wall","Wall","Wall","Wall","Wall","Wall","Wall","Wall","Wall","Wall","Wall","Wall","Wall","Wall","Wall","Wall","Wall","Wall","Floor","Floor","Floor","Floor","Floor","Floor","Wall","Wall","Floor","Wall","Wall","Wall","Wall","Wall","Wall","Wall","Wall","Wall","Wall","Wall","Wall","Wall","Wall","Wall","Wall","Wall","Wall","Wall","Wall","Floor","Floor","Floor","Floor","Floor","Floor","Floor","Floor","Floor","Wall","Wall","Wall","Wall","Wall","Wall","Wall","Wall","Wall","Wall","Wall","Wall","Wall","Wall","Floor","Floor","Floor","Floor","Floor","Floor","Floor","Wall","Wall","Wall","Wall","Wall","Wall","Wall","Wall","Wall","Wall","Wall","Wall","Wall","Wall","Wall","Wall","Wall","Wall","Wall","Wall","Wall","Floor","Floor","Floor","Floor","Floor","Floor","Wall","Wall","Floor","Wall","Wall","Wall","Wall","Wall","Wall","Wall","Wall","Wall","Wall","Wall","Wall","Wall","Wall","Wall","Wall","Wall","Wall","Wall","Wall","Wall","Wall","Wall","Floor","Wall","Wall","Wall","Wall","Wall","Wall","Wall","Wall","Wall","Wall","Wall","Wall","Wall","Wall","Wall","Wall","Wall","Wall","Wall","Floor","Floor","Floor","Floor","Floor","Floor","Floor","Wall","Wall","Wall","Wall","Wall","Wall","Wall","Wall","Wall","Wall","Wall","Wall","Wall","Wall","Wall","Wall","Wall","Wall","Wall","Wall","Wall","Wall","Wall","Wall","Wall","Floor","Wall","Wall","Wall","Floor","Wall","Wall","Wall","Wall","Wall","Wall","Wall","Wall","Wall","Wall","Wall","Wall","Wall","Wall","Wall","Wall","Wall","Wall","Wall","Wall","Wall","Wall","Wall","Floor","Wall","Wall","Wall","Wall","Wall","Wall","Wall","Wall","Wall","Wall","Wall","Wall","Wall","Wall","Wall","Wall","Wall","Wall","Wall","Floor","Floor","Floor","Floor","Floor","Floor","Floor","Wall","Wall","Wall","Wall","Wall","Wall","Wall","Wall","Wall","Wall","Wall","Wall","Wall","Wall","Wall","Wall","Wall","Wall","Wall","Wall","Wall","Wall","Wall","Wall","Wall","Floor","Wall","Wall","Wall","Floor","Wall","Wall","Wall","Wall","Wall","Wall","Wall","Wall","Wall","Wall","Wall","Wall","Wall","Wall","Wall","Wall","Wall","Wall","Wall","Wall","Wall","Wall","Wall","Floor","Wall","Wall","Wall","Wall","Wall","Wall","Wall","Wall","Wall","Wall","Wall","Wall","Wall","Wall","Wall","Wall","Wall","Wall","Wall","Floor","Wall","Wall","Wall","Wall","Wall","Wall","Wall","Wall","Wall","Wall","Wall","Wall","Wall","Wall","Wall","Wall","Wall","Wall","Wall","Wall","Wall","Wall","Wall","Wall","Wall","Wall","Wall","Wall","Wall","Wall","Wall","Floor","Wall","Wall","Wall","Floor","Wall","Wall","Wall","Wall","Wall","Wall","Wall","Wall","Wall","Wall","Wall","Wall","Wall","Wall","Wall","Wall","Wall","Wall","Wall","Wall","Wall","Wall","Wall","Floor","Wall","Wall","Wall","Wall","Wall","Wall","Wall","Wall","Wall","Wall","Wall","Wall","Wall","Wall","Wall","Wall","Wall","Wall","Floor","Floor","Floor","Floor","Floor","Floor","Floor","Floor","Floor","Wall","Wall","Wall","Wall","Wall","Wall","Wall","Wall","Wall","Wall","Wall","Wall","Wall","Wall","Wall","Wall","Wall","Wall","Wall","Wall","Wall","Wall","Wall","Wall","Floor","Wall","Wall","Wall","Floor","Wall","Wall","Wall","Wall","Wall","Wall","Wall","Wall","Wall","Wall","Wall","Wall","Wall","Wall","Wall","Wall","Wall","Wall","Wall","Wall","Wall","Wall","Wall","Floor","Wall","Wall","Wall","Wall","Wall","Wall","Wall","Wall","Wall","Wall","Wall","Wall","Wall","Wall","Wall","Wall","Wall","Wall","Floor","Floor","Floor","Floor","Floor","Floor","Floor","Floor","Floor","Wall","Wall","Wall","Wall","Wall","Wall","Wall","Wall","Wall","Wall","Wall","Wall","Wall","Wall","Wall","Wall","Wall","Wall","Wall","Wall","Wall","Wall","Wall","Wall","Floor","Wall","Wall","Wall","Floor","Wall","Wall","Wall","Wall","Wall","Wall","Floor","Floor","Floor","Floor","Floor","Floor","Floor","Floor","Floor","Floor","Floor","Floor","Floor","Floor","Floor","Floor","Floor","Floor","Floor","Floor","Floor","Floor","Floor","Floor","Floor","Floor","Floor","Floor","Floor","Floor","Floor","Floor","Floor","Floor","Floor","Floor","Floor","Floor","Floor","DownStairs","Floor","Floor","Floor","Floor","Floor","Wall","Wall","Wall","Wall","Wall","Wall","Wall","Wall","Wall","Wall","Wall","Wall","Wall","Wall","Wall","Wall","Wall","Wall","Wall","Wall","Wall","Wall","Wall","Wall","Floor","Wall","Wall","Wall","Floor","Wall","Wall","Wall","Wall","Wall","Wall","Floor","Wall","Wall","Wall","Wall","Wall","Wall","Wall","Wall","Wall","Wall","Wall","Wall","Wall","Wall","Wall","Wall","Floor","Wall","Wall","Wall","Wall","Wall","Wall","Wall","Wall","Wall","Wall","Wall","Wall","Wall","Wall","Wall","Wall","Wall","Wall","Floor","Floor","Floor","Floor","Floor","Floor","Floor","Floor","Floor","Wall","Wall","Wall","Wall","Wall","Wall","Wall","Wall","Wall","Wall","Wall","Wall","Wall","Wall","Wall","Wall","Wall","Wall","Wall","Wall","Wall","Wall","Wall","Wall","Floor","Wall","Wall","Wall","Floor","Wall","Wall","Wall","Wall","Wall","Wall","Floor","Wall","Wall","Wall","Wall","Wall","Wall","Wall","Wall","Wall","Wall","Wall","Wall","Wall","Wall","Wall","Wall","Floor","Wall","Wall","Wall","Wall","Wall","Wall","Wall","Wall","Wall","Wall","Wall","Wall","Wall","Wall","Wall","Wall","Wall","Wall","Floor","Floor","Floor","Floor","Floor","Floor","Floor","Floor","Floor","Wall","Wall","Wall","Wall","Wall","Wall","Wall","Wall","Wall","Wall","Wall","Wall","Wall","Wall","Wall","Wall","Wall","Wall","Wall","Wall","Wall","Wall","Wall","Wall","Floor","Wall","Wall","Wall","Floor","Wall","Wall","Wall","Wall","Wall","Wall","Floor","Wall","Wall","Wall","Wall","Wall","Wall","Wall","Wall","Wall","Wall","Wall","Wall","Wall","Wall","Wall","Wall","Floor","Wall","Wall","Wall","Wall","Wall","Wall","Wall","Wall","Wall","Wall","Wall","Wall","Wall","Wall","Wall","Wall","Wall","Wall","Floor","Floor","Floor","Floor","Floor","Floor","Floor","Floor","Floor","Wall","Wall","Wall","Wall","Wall","Wall","Wall","Wall","Wall","Wall","Wall","Wall","Wall","Wall","Wall","Wall","Wall","Wall","Wall","Wall","Wall","Wall","Wall","Wall","Floor","Wall","Wall","Wall","Floor","Wall","Wall","Wall","Wall","Wall","Wall","Floor","Wall","Wall","Wall","Wall","Wall","Wall","Wall","Wall","Wall","Wall","Wall","Wall","Wall","Wall","Wall","Wall","Floor","Wall","Wall","Wall","Wall","Wall","Wall","Wall","Wall","Wall","Wall","Wall","Wall","Wall","Wall","Wall","Wall","Wall","Wall","Wall","Floor","Wall","Wall","Wall","Wall","Wall","Wall","Wall","Wall","Wall","Wall","Wall","Wall","Wall","Wall","Wall","Wall","Wall","Wall","Wall","Wall","Wall","Wall","Wall","Wall","Wall","Wall","Wall","Wall","Wall","Wall","Wall","Floor","Wall","Wall","Wall","Floor","Wall","Wall","Wall","Wall","Wall","Wall","Floor","Wall","Wall","Wall","Wall","Wall","Wall","Wall","Wall","Wall","Wall","Wall","Wall","Wall","Wall","Wall","Floor","Floor","Floor","Floor","Floor","Floor","Floor","Floor","Wall","Wall","Wall","Wall","Wall","Wall","Wall","Wall","Wall","Wall","Wall","Wall","Wall","Floor","Wall","Wall","Wall","Wall","Wall","Wall","Wall","Wall","Wall","Wall","Wall","Wall","Wall","Wall","Wall","Wall","Wall","Wall","Wall","Wall","Wall","Wall","Wall","Wall","Wall","Wall","Wall","Wall","Wall","Wall","Wall","Floor","Floor","Floor","Floor","Floor","Floor","Floor","Floor","Floor","Wall","Wall","Floor","Wall","Wall","Wall","Wall","Wall","Wall","Wall","Wall","Wall","Wall","Wall","Wall","Wall","Wall","Wall","Floor","Floor","Floor","Floor","Floor","Floor","Floor","Floor","Wall","Wall","Wall","Wall","Wall","Wall","Wall","Wall","Wall","Wall","Wall","Wall","Wall","Floor","Wall","Wall","Wall","Wall","Wall","Wall","Wall","Wall","Wall","Wall","Wall","Wall","Wall","Wall","Wall","Wall","Wall","Wall","Wall","Wall","Wall","Wall","Floor","Floor","Floor","Floor","Floor","Floor","Wall","Wall","Wall","Floor","Floor","Floor","Floor","Floor","Floor","Floor","Floor","Floor","Wall","Wall","Floor","Wall","Wall","Wall","Wall","Wall","Wall","Wall","Wall","Wall","Wall","Wall","Wall","Wall","Wall","Wall","Floor","Floor","Floor","Floor","Floor","Floor","Floor","Floor","Wall","Wall","Wall","Wall","Wall","Wall","Wall","Wall","Wall","Wall","Wall","Wall","Wall","Floor","Wall","Wall","Wall","Wall","Wall","Wall","Wall","Wall","Wall","Wall","Wall","Wall","Wall","Wall","Wall","Wall","Wall","Wall","Wall","Wall","Wall","Wall","Floor","Floor","Floor","Floor","Floor","Floor","Wall","Wall","Wall","Floor","Floor","Floor","Floor","Floor","Floor","Floor","Floor","Floor","Floor","Floor","Floor","Floor","Floor","Floor","Floor","Floor","Floor","Floor","Floor","Floor","Floor","Floor","Floor","Floor","Floor","Floor","Floor","Floor","Floor","Floor","Floor","Floor","Floor","Floor","Floor","Floor","Floor","Floor","Floor","Floor","Floor","Floor","Floor","Floor","Floor","Floor","Floor","Floor","Wall","Wall","Wall","Wall","Wall","Wall","Wall","Wall","Wall","Wall","Wall","Wall","Wall","Wall","Wall","Wall","Wall","Wall","Wall","Wall","Wall","Wall","Floor","Floor","Floor","Floor","Floor","Floor","Floor","Floor","Floor","Floor","Floor","Floor","Floor","Floor","Floor","Floor","Floor","Floor","Floor","Floor","Floor","Floor","Floor","Floor","Floor","Floor","Floor","Floor","Floor","Floor","Floor","Floor","Floor","Floor","Floor","Floor","Floor","Floor","Floor","Floor","Floor","Floor","Floor","Floor","Wall","Wall","Floor","Wall","Wall","Wall","Wall","Wall","Wall","Wall","Wall","Wall","Wall","Floor","Wall","Wall","Wall","Wall","Wall","Wall","Wall","Wall","Wall","Wall","Wall","Wall","Wall","Wall","Wall","Wall","Wall","Wall","Wall","Wall","Wall","Wall","Floor","Floor","Floor","Floor","Floor","Floor","Wall","Wall","Wall","Floor","Floor","Floor","Floor","Floor","Floor","Floor","Floor","Floor","Wall","Wall","Floor","Wall","Wall","Wall","Wall","Wall","Wall","Wall","Wall","Wall","Wall","Wall","Wall","Wall","Wall","Wall","Floor","Floor","Floor","Floor","Floor","Floor","Floor","Floor","Wall","Wall","Floor","Wall","Wall","Wall","Wall","Wall","Wall","Wall","Wall","Wall","Wall","Floor","Wall","Wall","Wall","Wall","Wall","Wall","Wall","Wall","Wall","Wall","Wall","Wall","Wall","Wall","Wall","Wall","Wall","Wall","Wall","Wall","Wall","Wall","Floor","Floor","Floor","Floor","Floor","Floor","Wall","Wall","Wall","Floor","Floor","Floor","Floor","Floor","Floor","Floor","Floor","Floor","Wall","Wall","Floor","Wall","Wall","Wall","Wall","Wall","Wall","Wall","Wall","Wall","Wall","Wall","Wall","Wall","Wall","Wall","Floor","Floor","Floor","Floor","Floor","Floor","Floor","Floor","Wall","Wall","Floor","Wall","Wall","Wall","Wall","Wall","Wall","Wall","Wall","Wall","Wall","Floor","Wall","Wall","Wall","Wall","Wall","Wall","Wall","Wall","Wall","Wall","Wall","Wall","Wall","Wall","Wall","Wall","Wall","Wall","Wall","Wall","Wall","Wall","Floor","Floor","Floor","Floor","Floor","Floor","Wall","Wall","Wall","Floor","Floor","Floor","Floor","Floor","Floor","Floor","Floor","Floor","Wall","Wall","Floor","Wall","Wall","Wall","Wall","Wall","Wall","Wall","Wall","Wall","Wall","Wall","Wall","Wall","Wall","Wall","Floor","Floor","Floor","Floor","Floor","Floor","Floor","Floor","Wall","Wall","Floor","Wall","Wall","Wall","Wall","Wall","Wall","Wall","Wall","Wall","Wall","Floor","Wall","Wall","Wall","Wall","Wall","Wall","Wall","Wall","Wall","Wall","Wall","Wall","Wall","Wall","Wall","Wall","Wall","Wall","Wall","Wall","Wall","Wall","Floor","Floor","Floor","Floor","Floor","Floor","Wall","Wall","Wall","Floor","Wall","Wall","Wall","Wall","Wall","Wall","Wall","Wall","Wall","Wall","Floor","Wall","Wall","Wall","Wall","Wall","Wall","Wall","Wall","Wall","Wall","Wall","Wall","Wall","Wall","Wall","Floor","Floor","Floor","Floor","Floor","Floor","Floor","Floor","Wall","Wall","Floor","Wall","Wall","Wall","Wall","Wall","Wall","Wall","Floor","Floor","Floor","Floor","Floor","Floor","Floor","Floor","Floor","Wall","Wall","Wall","Wall","Wall","Wall","Wall","Wall","Wall","Wall","Wall","Wall","Wall","Wall","Wall","Wall","Wall","Wall","Wall","Wall","Wall","Wall","Wall","Wall","Wall","Wall","Floor","Wall","Wall","Wall","Wall","Wall","Wall","Wall","Wall","Wall","Wall","Floor","Wall","Wall","Wall","Wall","Wall","Wall","Wall","Wall","Wall","Wall","Wall","Wall","Wall","Wall","Wall","Wall","Floor","Wall","Wall","Wall","Wall","Wall","Wall","Wall","Wall","Floor","Wall","Wall","Wall","Wall","Wall","Wall","Wall","Floor","Floor","Floor","Floor","Floor","Floor","Floor","Floor","Floor","Wall","Wall","Wall","Wall","Wall","Wall","Wall","Wall","Wall","Wall","Wall","Wall","Wall","Wall","Wall","Wall","Wall","Wall","Wall","Wall","Wall","Wall","Wall","Floor","Floor","Floor","Floor","Floor","Floor","Floor","Floor","Floor","Wall","Wall","Wall","Wall","Wall","Floor","Wall","Wall","Wall","Wall","Wall","Wall","Wall","Wall","Wall","Wall","Wall","Wall","Wall","Wall","Wall","Wall","Floor","Wall","Wall","Wall","Wall","Wall","Floor","Floor","Floor","Floor","Floor","Floor","Floor","Floor","Floor","Wall","Wall","Floor","Floor","Floor","Floor","Floor","Floor","Floor","Floor","Floor","Wall","Wall","Wall","Wall","Wall","Wall","Wall","Wall","Wall","Wall","Wall","Wall","Wall","Wall","Wall","Wall","Wall","Wall","Wall","Wall","Wall","Wall","Wall","Floor","Floor","Floor","Floor","Floor","Floor","Floor","Floor","Floor","Wall","Wall","Wall","Wall","Wall","Floor","Wall","Wall","Wall","Wall","Wall","Wall","Wall","Wall","Wall","Wall","Wall","Wall","Wall","Floor","Floor","Floor","Floor","Floor","Floor","Floor","Floor","Wall","Floor","Floor","Floor","Floor","Floor","Floor","Floor","Floor","Floor","Wall","Wall","Floor","Floor","Floor","Floor","Floor","Floor","Floor","Floor","Floor","Wall","Wall","Wall","Wall","Wall","Wall","Wall","Wall","Wall","Wall","Wall","Wall","Wall","Wall","Wall","Wall","Wall","Wall","Wall","Wall","Wall","Wall","Wall","Floor","Floor","Floor","Floor","Floor","Floor","Floor","Floor","Floor","Wall","Wall","Wall","Wall","Wall","Floor","Wall","Wall","Wall","Wall","Wall","Wall","Wall","Wall","Wall","Wall","Wall","Wall","Wall","Floor","Floor","Floor","Floor","Floor","Floor","Floor","Floor","Wall","Floor","Floor","Floor","Floor","Floor","Floor","Floor","Floor","Floor","Wall","Wall","Floor","Floor","Floor","Floor","Floor","Floor","Floor","Floor","Floor","Wall","Wall","Wall","Wall","Wall","Wall","Wall","Wall","Wall","Wall","Wall","Wall","Wall","Wall","Wall","Wall","Wall","Wall","Wall","Wall","Wall","Wall","Wall","Floor","Floor","Floor","Floor","Floor","Floor","Floor","Floor","Floor","Floor","Floor","Floor","Floor","Floor","Floor","Floor","Floor","Floor","Floor","Floor","Floor","Floor","Floor","Floor","Floor","Floor","Floor","Floor","Floor","Floor","Floor","Floor","Floor","Floor","Floor","Floor","Floor","Floor","Floor","Floor","Floor","Floor","Floor","Floor","Floor","Floor","Wall","Wall","Floor","Floor","Floor","Floor","Floor","Floor","Floor","Floor","Floor","Wall","Wall","Wall","Wall","Wall","Wall","Wall","Wall","Wall","Wall","Wall","Wall","Wall","Wall","Wall","Wall","Wall","Wall","Wall","Wall","Wall","Wall","Wall","Floor","Floor","Floor","Floor","Floor","Floor","Floor","Floor","Floor","Wall","Wall","Floor","Floor","Floor","Floor","Floor","Floor","Floor","Floor","Floor","Wall","Wall","Wall","Wall","Wall","Wall","Wall","Wall","Floor","Floor","Floor","Floor","Floor","Floor","Floor","Floor","Wall","Floor","Floor","Floor","Floor","Floor","Floor","Floor","Floor","Floor","Wall","Wall","Floor","Floor","Floor","Floor","Floor","Floor","Floor","Floor","Floor","Wall","Wall","Wall","Wall","Wall","Wall","Wall","Wall","Wall","Wall","Wall","Wall","Wall","Wall","Wall","Wall","Wall","Wall","Wall","Wall","Wall","Wall","Wall","Floor","Floor","Floor","Floor","Floor","Floor","Floor","Floor","Floor","Wall","Wall","Floor","Floor","Floor","Floor","Floor","Floor","Floor","Floor","Floor","Wall","Wall","Wall","Wall","Wall","Wall","Wall","Wall","Floor","Floor","Floor","Floor","Floor","Floor","Floor","Floor","Wall","Floor","Floor","Floor","Floor","Floor","Floor","Floor","Floor","Floor","Wall","Wall","Floor","Floor","Floor","Floor","Floor","Floor","Floor","Floor","Floor","Wall","Wall","Wall","Wall","Wall","Wall","Wall","Wall","Wall","Wall","Wall","Wall","Wall","Wall","Wall","Wall","Wall","Wall","Wall","Wall","Wall","Wall","Wall","Wall","Wall","Wall","Wall","Wall","Wall","Wall","Wall","Wall","Wall","Wall","Floor","Floor","Floor","Floor","Floor","Floor","Floor","Floor","Floor","Wall","Wall","Wall","Wall","Wall","Wall","Wall","Wall","Floor","Floor","Floor","Floor","Floor","Floor","Floor","Floor","Wall","Floor","Floor","Floor","Floor","Floor","Floor","Floor","Floor","Floor","Wall","Wall","Floor","Floor","Floor","Floor","Floor","Floor","Floor","Floor","Floor","Wall","Wall","Wall","Wall","Wall","Wall","Wall","Wall","Wall","Wall","Wall","Wall","Wall","Wall","Wall","Wall","Wall","Wall","Wall","Wall","Wall","Wall","Wall","Wall","Wall","Wall","Wall","Wall","Wall","Wall","Wall","Wall","Wall","Wall","Floor","Floor","Floor","Floor","Floor","Floor","Floor","Floor","Floor","Wall","Wall","Wall","Wall","Wall","Wall","Wall","Wall","Floor","Floor","Floor","Floor","Floor","Floor","Floor","Floor","Wall","Floor","Floor","Floor","Floor","Floor","Floor","Floor","Floor","Floor","Wall","Wall","Wall","Wall","Wall","Wall","Wall","Wall","Wall","Wall","Wall","Wall","Wall","Wall","Wall","Wall","Wall","Wall","Wall","Wall","Wall","Wall","Wall","Wall","Wall","Wall","Wall","Wall","Wall","Wall","Wall","Wall","Wall","Wall","Wall","Wall","Wall","Wall","Wall","Wall","Wall","Wall","Wall","Wall","Wall","Floor","Floor","Floor","Floor","Floor","Floor","Floor","Floor","Floor","Wall","Wall","Wall","Wall","Wall","Wall","Wall","Wall","Wall","Wall","Wall","Wall","Wall","Wall","Wall","Wall","Wall","Floor","Floor","Floor","Floor","Floor","Floor","Floor","Floor","Floor","Wall","Wall","Wall","Wall","Wall","Wall","Wall","Wall","Wall","Wall","Wall","Wall","Wall","Wall","Wall","Wall","Wall","Wall","Wall","Wall","Wall","Wall","Wall","Wall","Wall","Wall","Wall","Wall","Wall","Wall","Wall","Wall","Wall","Wall","Wall","Wall","Wall","Wall","Wall","Wall","Wall","Wall","Wall","Wall","Wall","Floor","Floor","Floor","Floor","Floor","Floor","Floor","Floor","Floor","Wall","Wall","Wall","Wall","Wall","Wall","Wall","Wall","Wall","Wall","Wall","Wall","Wall","Wall","Wall","Wall","Wall","Wall","Wall","Wall","Wall","Wall","Wall","Wall","Wall","Wall","Wall","Wall","Wall","Wall","Wall","Wall","Wall","Wall","Wall","Wall","Wall","Wall","Wall","Wall","Wall","Wall","Wall","Wall","Wall","Wall","Wall","Wall","Wall","Wall","Wall","Wall","Wall","Wall","Wall","Wall","Wall","Wall","Wall","Wall","Wall","Wall","Wall","Wall","Wall","Wall","Wall","Wall","Wall","Wall","Wall","Floor","Floor","Floor","Floor","Floor","Floor","Floor","Floor","Floor","Wall","Wall","Wall","Wall","Wall","Wall","Wall","Wall","Wall","Wall","Wall","Wall","Wall","Wall","Wall","Wall","Wall","Wall","Wall","Wall","Wall","Wall","Wall","Wall","Wall","Wall","Wall","Wall","Wall","Wall","Wall","Wall","Wall","Wall","Wall","Wall","Wall","Wall","Wall","Wall","Wall","Wall","Wall","Wall","Wall","Wall","Wall","Wall","Wall","Wall","Wall","Wall","Wall","Wall","Wall","Wall","Wall","Wall","Wall","Wall","Wall","Wall","Wall","Wall","Wall","Wall","Wall","Wall","Wall","Wall","Wall","Floor","Floor","Floor","Floor","Floor","Floor","Floor","Floor","Floor","Wall","Wall","Wall","Wall","Wall","Wall","Wall","Wall","Wall","Wall","Wall","Wall","Wall","Wall","Wall","Wall","Wall","Wall","Wall","Wall","Wall","Wall","Wall","Wall","Wall","Wall","Wall","Wall","Wall","Wall","Wall","Wall","Wall","Wall","Wall","Wall","Wall","Wall","Wall","Wall","Wall","Wall","Wall","Wall","Wall","Wall","Wall","Wall","Wall","Wall","Wall","Wall","Wall","Wall","Wall","Wall","Wall","Wall","Wall","Wall","Wall","Wall","Wall","Wall","Wall","Wall","Wall","Wall","Wall","Wall","Wall","Floor","Floor","Floor","Floor","Floor","Floor","Floor","Floor","Floor","Wall","Wall","Wall","Wall","Wall","Wall","Wall","Wall","Wall","Wall","Wall","Wall","Wall","Wall","Wall","Wall","Wall","Wall","Wall","Wall","Wall","Wall","Wall","Wall","Wall","Wall","Wall","Wall","Wall","Wall","Wall","Wall","Wall","Wall","Wall","Wall","Wall","Wall","Wall","Wall","Wall","Wall","Wall","Wall","Wall","Wall","Wall","Wall","Wall","Wall","Wall","Wall","Wall","Wall","Wall","Wall","Wall","Wall","Wall","Wall","Wall","Wall","Wall","Wall","Wall","Wall","Wall","Wall","Wall","Wall","Wall","Wall","Wall","Wall","Wall","Wall","Wall","Wall","Wall","Wall","Wall","Wall","Wall","Wall","Wall","Wall","Wall","Wall","Wall","Wall","Wall","Wall","Wall","Wall","Wall","Wall","Wall","Wall","Wall","Wall","Wall","Wall","Wall","Wall","Wall","Wall","Wall","Wall","Wall","Wall","Wall","Wall","Wall","Wall","Wall","Wall","Wall","Wall","Wall","Wall","Wall","Wall","Wall","Wall","Wall","Wall","Wall","Wall"],"rooms":[{"x1":10,"x2":16,"y1":1,"y2":9},{"x1":11,"x2":20,"y1":28,"y2":34},{"x1":39,"x2":47,"y1":29,"y2":36},{"x1":15,"x2":23,"y1":19,"y2":26},{"x1":63,"x2":69,"y1":4,"y2":10},{"x1":59,"x2":68,"y1":26,"y2":35},{"x1":41,"x2":49,"y1":18,"y2":27},{"x1":48,"x2":57,"y1":28,"y2":37},{"x1":39,"x2":48,"y1":2,"y2":8},{"x1":5,"x2":11,"y1":20,"y2":27},{"x1":22,"x2":31,"y1":32,"y2":41},{"x1":61,"x2":70,"y1":11,"y2":17}],"width":80,"height":43,"revealed_tiles":[false,false,false,false,false,false,false,false,false,false,false,false,false,false,false,false,false,false,false,false,false,false,false,false,false,false,false,false,false,false,false,false,false,false,false,false,false,false,false,false,false,false,false,false,false,false,false,false,false,false,false,false,false,false,false,false,false,false,false,false,false,false,false,false,false,false,false,false,false,false,false,false,false,false,false,false,false,false,false,false,false,false,false,false,false,false,false,false,false,false,true,true,true,true,true,true,true,true,false,false,false,false,false,false,false,false,false,false,false,false,false,false,false,false,false,false,false,false,false,false,false,false,false,false,false,false,false,false,false,false,false,false,false,false,false,false,false,false,false,false,false,false,false,false,false,false,false,false,false,false,false,false,false,false,false,false,false,false,false,false,false,false,false,false,false,false,false,false,false,false,true,true,true,true,true,true,true,true,false,false,false,false,false,false,false,false,false,false,false,false,false,false,false,false,false,false,false,false,false,true,true,true,true,true,true,true,true,true,true,true,false,false,false,false,false,false,false,false,false,false,false,false,false,false,false,false,false,false,false,false,false,false,false,false,false,false,false,false,false,false,false,false,false,false,false,false,false,false,false,false,true,true,true,true,true,true,true,true,false,false,false,false,false,false,false,false,false,false,false,false,false,false,false,false,false,false,false,false,false,true,true,true,true,true,true,true,true,true,true,true,false,false,false,false,false,false,false,false,false,false,false,false,false,false,false,false,false,false,false,false,false,false,false,false,false,false,false,false,false,false,false,false,false,false,false,false,false,false,false,false,true,true,true,true,true,true,true,true,false,false,false,false,false,false,false,false,false,false,false,false,false,false,false,false,false,false,false,false,false,true,true,true,true,true,true,true,true,true,true,true,false,false,false,false,false,false,false,false,false,false,false,false,false,true,true,true,true,true,true,true,true,false,false,false,false,false,false,false,false,false,false,false,false,false,false,false,false,false,false,false,true,true,true,true,true,true,true,true,false,false,false,false,false,false,false,false,false,false,false,false,false,false,false,false,false,false,false,false,false,true,true,true,true,true,true,true,true,true,true,true,false,false,false,false,false,false,false,false,false,false,false,false,false,true,true,true,true,true,true,true,true,false,false,false,false,false,false,false,false,false,false,false,false,false,false,false,false,false,false,false,true,true,true,true,true,true,true,true,true,true,true,true,true,true,true,true,true,true,true,true,true,true,true,true,true,true,true,true,true,true,true,true,true,true,true,true,true,true,true,true,true,true,true,true,true,true,true,true,true,true,true,true,true,true,true,true,true,true,true,true,true,false,false,false,false,false,false,false,false,false,false,false,false,false,false,false,false,false,false,false,true,true,true,true,true,true,true,true,true,true,true,true,true,true,true,true,true,true,true,true,true,true,true,true,true,true,true,true,true,true,true,true,true,true,true,true,true,true,true,true,true,true,true,true,true,true,true,true,true,true,true,true,true,true,true,true,true,true,true,true,true,false,false,false,false,false,false,false,false,false,false,false,false,false,false,false,false,false,false,false,true,true,true,true,true,true,true,true,true,true,true,true,true,true,true,true,true,true,true,true,true,true,true,true,true,true,true,true,true,true,true,true,true,true,true,true,true,true,true,true,true,true,true,true,true,true,true,true,true,true,true,true,true,true,true,true,true,true,true,true,true,false,false,false,false,false,false,false,false,false,false,false,false,false,false,false,false,false,false,false,true,true,true,true,true,true,true,true,true,true,true,false,false,false,false,false,false,false,false,false,false,false,false,false,false,false,false,false,false,true,true,true,true,true,true,true,true,true,true,true,false,false,false,false,false,false,false,false,false,false,false,false,true,true,true,true,true,true,true,true,true,false,false,false,false,false,false,false,false,false,false,false,false,false,false,false,false,false,false,false,true,true,true,true,true,true,true,true,true,true,true,false,false,false,false,false,false,false,false,false,false,false,false,false,false,false,false,false,false,false,false,false,true,true,true,false,false,false,false,false,false,false,false,false,false,false,false,false,false,false,false,false,true,true,true,true,true,true,true,true,true,false,false,false,false,false,false,false,false,false,false,false,false,false,false,false,false,false,false,false,false,false,false,false,true,true,true,false,true,true,true,false,false,false,false,false,false,false,false,false,false,false,false,false,false,false,false,false,false,false,false,false,true,true,true,false,false,false,false,false,false,false,false,false,false,false,false,false,false,false,false,true,true,true,true,true,true,true,true,true,true,true,false,false,false,false,false,false,false,false,false,false,false,false,false,false,false,false,false,false,false,false,false,false,true,true,true,false,true,true,true,false,false,false,false,false,false,false,false,false,false,false,false,false,false,false,false,false,false,false,false,false,true,true,true,false,false,false,false,false,false,false,false,false,false,false,false,false,false,false,false,true,true,true,true,true,true,true,true,true,true,true,false,false,false,false,false,false,false,false,false,false,false,false,false,false,false,false,false,false,false,false,false,false,true,true,true,false,true,true,true,false,false,false,false,false,false,false,false,false,false,false,false,false,false,false,false,false,false,false,false,false,true,true,true,false,false,false,false,false,false,false,false,false,false,true,true,true,true,true,true,true,true,true,true,true,true,true,true,true,true,true,false,false,false,false,false,false,false,false,false,false,false,false,false,false,false,false,false,false,false,false,false,false,true,true,true,false,true,true,true,false,false,false,false,true,true,true,false,false,false,false,false,false,false,false,false,false,false,false,false,false,true,true,true,false,false,false,false,false,false,false,false,false,false,true,true,true,true,true,true,true,true,true,true,true,true,true,true,true,true,true,false,false,false,false,false,false,false,false,false,false,false,false,false,false,false,false,false,false,false,false,false,false,true,true,true,false,true,true,true,false,false,false,false,true,true,true,false,false,false,false,false,false,false,false,false,false,false,false,false,false,true,true,true,false,false,false,false,false,false,false,false,false,false,true,true,true,true,true,true,true,true,true,true,true,true,true,true,true,true,true,false,false,false,false,false,false,false,false,false,false,false,false,false,false,false,false,false,false,false,false,false,false,true,true,true,false,true,true,true,false,false,false,false,true,true,true,false,false,false,false,false,false,false,false,false,false,false,false,false,false,true,true,true,false,false,false,false,false,false,false,false,false,false,false,false,false,false,false,false,true,true,true,true,true,true,true,true,true,true,true,false,false,false,false,false,false,false,false,false,false,false,false,false,false,false,false,false,false,false,false,false,false,true,true,true,false,true,true,true,false,false,false,false,true,true,true,false,false,false,false,false,false,false,false,false,false,false,false,false,false,true,true,true,false,false,false,false,false,false,false,false,false,false,false,false,false,false,false,false,true,true,true,true,true,true,true,true,true,true,true,false,false,false,false,false,false,false,false,false,false,false,false,false,false,false,false,false,false,false,false,false,false,true,true,true,false,true,true,true,false,false,false,false,true,true,true,false,false,false,false,false,false,false,false,false,false,false,false,false,true,true,true,true,true,true,true,true,true,true,false,false,false,false,false,false,false,false,false,false,true,true,true,true,true,true,true,true,true,true,true,false,false,false,false,false,false,false,false,false,false,false,false,false,false,false,false,false,false,false,false,false,false,true,true,true,true,true,true,true,true,true,true,true,true,true,true,false,false,false,false,false,false,false,false,false,false,false,false,false,true,true,true,true,true,true,true,true,true,true,false,false,false,false,false,false,false,false,false,false,false,true,true,true,false,false,false,false,false,false,false,false,false,false,false,false,false,false,false,false,false,false,false,false,false,false,false,false,false,false,false,false,false,true,true,true,true,true,true,true,true,true,true,true,true,true,true,false,false,false,false,false,false,false,false,false,false,false,false,false,true,true,true,true,true,true,true,true,true,true,false,false,false,false,false,false,false,false,false,false,false,true,true,true,false,false,false,false,false,false,false,false,false,false,false,false,false,false,false,false,false,false,false,false,false,false,false,false,false,false,false,false,false,true,true,true,true,true,true,true,true,true,true,true,true,true,true,true,true,true,true,true,true,true,true,true,true,true,true,true,true,true,true,true,true,true,true,true,true,true,true,true,true,true,true,true,true,true,true,true,true,true,true,true,false,false,false,false,false,false,false,false,false,false,false,false,false,false,false,false,false,false,false,false,false,false,true,true,true,true,true,true,true,true,true,true,true,true,true,true,true,true,true,true,true,true,true,true,true,true,true,true,true,true,true,true,true,true,true,true,true,true,true,true,true,true,true,true,true,true,true,true,true,true,true,true,true,true,true,true,true,true,true,true,false,false,false,false,false,false,false,false,false,false,false,false,false,false,false,false,false,false,false,false,false,false,true,true,true,true,true,true,true,true,true,true,true,true,true,true,true,true,true,true,true,true,true,true,true,true,true,true,true,true,true,true,true,true,true,true,true,true,true,true,true,true,true,true,true,true,true,true,true,true,true,true,true,true,true,true,true,true,true,true,false,false,false,false,false,false,false,false,false,false,false,false,false,false,false,false,false,false,false,false,false,false,true,true,true,true,true,true,true,true,true,true,true,true,true,true,true,true,true,true,true,true,true,true,true,true,true,true,true,true,true,true,true,true,true,true,true,true,true,true,true,true,true,true,true,true,true,true,true,false,false,false,false,false,false,false,false,true,true,true,false,false,false,false,false,false,false,false,false,false,false,false,false,false,false,false,false,false,false,false,false,false,false,false,false,false,false,false,false,true,true,true,true,true,true,true,true,true,true,true,true,true,true,false,false,false,false,false,false,false,false,false,false,false,false,false,true,true,true,true,true,true,true,true,true,true,true,true,true,false,false,false,false,false,false,false,false,true,true,true,false,false,false,false,false,false,false,false,false,false,false,false,false,false,false,false,false,false,false,false,false,false,false,false,false,false,false,false,false,true,true,true,true,true,true,true,true,true,true,true,true,true,true,false,false,false,false,false,false,false,false,false,false,false,false,false,true,true,true,true,true,true,true,true,true,true,true,true,true,false,false,false,false,false,true,true,true,true,true,true,true,true,true,true,true,false,false,false,false,false,false,false,false,false,false,false,false,false,false,false,false,false,false,false,false,false,false,false,false,true,true,true,true,true,true,true,true,true,true,true,true,true,true,false,false,false,false,false,false,false,false,false,false,false,false,false,true,true,true,true,true,true,true,true,true,true,true,true,true,false,false,false,false,false,true,true,true,true,true,true,true,true,true,true,true,false,false,false,false,false,false,false,false,false,false,false,false,false,false,false,false,false,false,false,false,false,true,true,true,true,true,true,true,true,true,true,true,false,false,false,true,true,true,false,false,false,false,false,false,false,false,false,false,false,false,false,true,true,true,true,true,true,true,true,true,true,true,true,true,true,true,true,true,true,true,true,true,true,true,true,true,true,true,true,true,false,false,false,false,false,false,false,false,false,false,false,false,false,false,false,false,false,false,false,false,false,true,true,true,true,true,true,true,true,true,true,true,false,false,false,true,true,true,false,false,false,false,false,false,false,false,false,false,false,true,true,true,true,true,true,true,true,true,true,true,true,true,true,true,true,true,true,true,true,true,true,true,true,true,true,true,true,true,true,true,false,false,false,false,false,false,false,false,false,false,false,false,false,false,false,false,false,false,false,false,false,true,true,true,true,true,true,true,true,true,true,true,false,false,false,true,true,true,false,false,false,false,false,false,false,false,false,false,false,true,true,true,true,true,true,true,true,true,true,true,true,true,true,true,true,true,true,true,true,true,true,true,true,true,true,true,true,true,true,true,false,false,false,false,false,false,false,false,false,false,false,false,false,false,false,false,false,false,false,false,false,true,true,true,true,true,true,true,true,true,true,true,true,true,true,true,true,true,true,true,true,true,true,true,true,true,true,true,true,true,true,true,true,true,true,true,true,true,true,true,true,true,true,true,true,true,true,true,true,true,true,true,true,true,true,true,true,true,true,true,false,false,false,false,false,false,false,false,false,false,false,false,false,false,false,false,false,false,false,false,false,true,true,true,true,true,true,true,true,true,true,true,true,true,true,true,true,true,true,true,true,true,true,true,true,true,true,true,true,true,true,true,true,true,true,true,true,true,true,true,true,true,true,true,true,true,true,true,true,true,true,true,true,true,true,true,true,true,true,true,false,false,false,false,false,false,false,false,false,false,false,false,false,false,false,false,false,false,false,false,false,true,true,true,true,true,true,true,true,true,true,true,true,true,true,true,true,true,true,true,true,true,true,true,true,true,true,true,true,true,true,true,true,true,true,true,true,true,true,true,true,true,true,true,true,true,true,true,true,true,true,true,true,true,true,true,true,true,true,true,false,false,false,false,false,false,false,false,false,false,false,false,false,false,false,false,false,false,false,false,false,true,true,true,true,true,true,true,true,true,true,true,true,true,true,true,true,true,true,true,true,true,true,false,false,false,false,false,false,true,true,true,true,true,true,true,true,true,true,true,true,true,true,true,true,true,true,true,true,true,true,true,true,true,true,true,true,true,true,true,false,false,false,false,false,false,false,false,false,false,false,false,false,false,false,false,false,false,false,false,false,true,true,true,true,true,true,true,true,true,true,true,true,true,true,true,true,true,true,true,true,true,true,false,false,false,false,false,false,true,true,true,true,true,true,true,true,true,true,true,true,true,true,true,true,true,true,true,true,true,true,true,true,true,true,true,true,true,true,true,false,false,false,false,false,false,false,false,false,false,false,false,false,false,false,false,false,false,false,false,false,false,false,false,false,false,false,false,false,false,false,false,true,true,true,true,true,true,true,true,true,true,true,false,false,false,false,false,false,true,true,true,true,true,true,true,true,true,true,true,true,true,true,true,true,true,true,true,true,true,true,true,true,true,true,true,true,true,true,true,false,false,false,false,false,false,false,false,false,false,false,false,false,false,false,false,false,false,false,false,false,false,false,false,false,false,false,false,false,false,false,false,true,true,true,true,true,true,true,true,true,true,true,false,false,false,false,false,false,true,true,true,true,true,true,true,true,true,true,true,true,true,true,true,true,true,true,true,true,false,false,false,false,false,false,false,false,false,false,false,false,false,false,false,false,false,false,false,false,false,false,false,false,false,false,false,false,false,false,false,false,false,false,false,false,false,false,false,false,false,false,false,true,true,true,true,true,true,true,true,true,true,true,false,false,false,false,false,false,false,false,false,false,false,false,false,false,false,true,true,true,true,true,true,true,true,true,true,true,false,false,false,false,false,false,false,false,false,false,false,false,false,false,false,false,false,false,false,false,false,false,false,false,false,false,false,false,false,false,false,false,false,false,false,false,false,false,false,false,false,false,false,true,true,true,true,true,true,true,true,true,true,true,false,false,false,false,false,false,false,false,false,false,false,false,false,false,false,false,false,false,false,false,false,false,false,false,false,false,false,false,false,false,false,false,false,false,false,false,false,false,false,false,false,false,false,false,false,false,false,false,false,false,false,false,false,false,false,false,false,false,false,false,false,false,false,false,false,false,false,false,false,true,true,true,true,true,true,true,true,true,true,true,false,false,false,false,false,false,false,false,false,false,false,false,false,false,false,false,false,false,false,false,false,false,false,false,false,false,false,false,false,false,false,false,false,false,false,false,false,false,false,false,false,false,false,false,false,false,false,false,false,false,false,false,false,false,false,false,false,false,false,false,false,false,false,false,false,false,false,false,false,false,false,false,false,false,false,false,false,false,false,false,false,false,false,false,false,false,false,false,false,false,false,false,false,false,false,false,false,false,false,false,false,false,false,false,false,false,false,false,false,false,false,false,false,false,false,false,false,false,false,false,false,false,false,false,false,false,false,false,false,false,false,false,false,false,false,false,false,false,false,false,false,false,false,false,false,false,false,false,false,false,false,false,false,false,false,false,false,false,false,false,false,false,false,false,false,false,false,false,false,false,false,false,false,false,false,false,false,false,false,false,false,false,false,false,false,false,false,false,false,false,false,false,false,false,false,false,false,false,false,false,false,false,false,false,false,false,false],"visible_tiles":[false,false,false,false,false,false,false,false,false,false,false,false,false,false,false,false,false,false,false,false,false,false,false,false,false,false,false,false,false,false,false,false,false,false,false,false,false,false,false,false,false,false,false,false,false,false,false,false,false,false,false,false,false,false,false,false,false,false,false,false,false,false,false,false,false,false,false,false,false,false,false,false,false,false,false,false,false,false,false,false,false,false,false,false,false,false,false,false,false,false,false,false,false,false,false,false,false,false,false,false,false,false,false,false,false,false,false,false,false,false,false,false,false,false,false,false,false,false,false,false,false,false,false,false,false,false,false,false,false,false,false,false,false,false,false,false,false,false,false,false,false,false,false,false,false,false,false,false,false,false,false,false,false,false,false,false,false,false,false,false,false,false,false,false,false,false,false,false,false,false,false,false,false,false,false,false,false,false,false,false,false,false,false,false,false,false,false,false,false,false,false,false,false,false,false,false,false,false,false,false,false,false,false,false,false,false,false,false,false,false,false,false,false,false,false,false,false,false,false,false,false,false,false,false,false,false,false,false,false,false,false,false,false,false,false,false,false,false,false,false,false,false,false,false,false,false,false,false,false,false,false,false,false,false,false,false,false,false,false,false,false,false,false,false,false,false,false,false,false,false,false,false,false,false,false,false,false,false,false,false,false,false,false,false,false,false,false,false,false,false,false,false,false,false,false,false,false,false,false,false,false,false,false,false,false,false,false,false,false,false,false,false,false,false,false,false,false,false,false,false,false,false,false,false,false,false,false,false,false,false,false,false,false,false,false,false,false,false,false,false,false,false,false,false,false,false,false,false,false,false,false,false,false,false,false,false,false,false,false,false,false,false,false,false,false,false,false,false,false,false,false,false,false,false,false,false,false,false,false,false,false,false,false,false,false,false,false,false,false,false,false,false,false,false,false,false,false,false,false,false,false,false,false,false,false,false,false,false,false,false,false,false,false,false,false,false,false,false,false,false,false,false,false,false,false,false,false,false,false,false,false,false,false,false,false,false,false,false,false,false,false,false,false,false,false,false,false,false,false,false,false,false,false,false,false,false,false,false,false,false,false,false,false,false,false,false,false,false,false,false,false,false,false,false,false,false,false,false,false,false,false,false,false,false,false,false,false,false,false,false,false,false,false,false,false,false,false,false,false,false,false,false,false,false,false,false,false,false,false,false,false,false,false,false,false,false,false,false,false,false,false,false,false,false,false,false,false,false,false,false,false,false,false,false,false,false,false,false,false,false,false,false,false,false,false,false,false,false,false,false,false,false,false,false,false,false,false,false,false,false,false,false,false,false,false,false,false,false,false,false,false,false,false,false,false,false,false,false,false,false,false,false,false,false,false,false,false,false,false,false,false,false,false,false,false,false,false,false,false,false,false,false,false,false,false,false,false,false,false,false,false,false,false,false,false,false,false,false,false,false,false,false,false,false,false,false,false,false,false,false,false,false,false,false,false,false,false,false,false,false,false,false,false,false,false,false,false,false,false,false,false,false,false,false,false,false,false,false,false,false,false,false,false,false,false,false,false,false,false,false,false,false,false,false,false,false,false,false,false,false,false,false,false,false,false,false,false,false,false,false,false,false,false,false,false,false,false,false,false,false,false,false,false,false,false,false,false,false,false,false,false,false,false,false,false,false,false,false,false,false,false,false,false,false,false,false,false,false,false,false,false,false,false,false,false,false,false,false,false,false,false,false,false,false,false,false,false,false,false,false,false,false,false,false,false,false,false,false,false,false,false,false,false,false,false,false,false,false,false,false,false,false,false,false,false,false,false,false,false,false,false,false,false,false,false,false,false,false,false,false,false,false,false,false,false,false,false,false,false,false,false,false,false,false,false,false,false,false,false,false,false,false,false,false,false,false,false,false,false,false,false,false,false,false,false,false,false,false,false,false,false,false,false,false,false,false,false,false,false,false,false,false,false,false,false,false,false,false,false,false,false,false,false,false,false,false,false,false,false,false,false,false,false,false,false,false,false,false,false,false,false,false,false,false,false,false,false,false,false,false,false,false,false,false,false,false,false,false,false,false,false,false,false,false,false,false,false,false,false,false,false,false,false,false,false,false,false,false,false,false,false,false,false,false,false,false,false,false,false,false,false,false,false,false,false,false,false,false,false,false,false,false,false,false,false,false,false,false,false,false,false,false,false,false,false,false,false,false,false,false,false,false,false,false,false,false,false,false,false,false,false,false,false,false,false,false,false,false,false,false,false,false,false,false,false,false,false,false,false,false,false,false,false,false,false,false,false,false,false,false,false,false,false,false,false,false,false,false,false,false,false,false,false,false,false,false,false,false,false,false,false,false,false,false,false,false,false,false,false,false,false,false,false,false,false,false,false,false,false,false,false,false,false,false,false,false,false,false,false,false,false,false,false,false,false,false,false,false,false,false,false,false,false,false,false,false,false,false,false,false,false,false,false,false,false,false,false,false,false,false,false,false,false,false,false,false,false,false,false,false,false,false,false,false,false,false,false,false,false,false,false,false,false,false,false,false,false,false,false,false,false,false,false,false,false,false,false,false,false,false,false,false,false,false,false,false,false,false,false,false,false,false,false,false,false,false,false,false,false,false,false,false,false,false,false,false,false,false,false,false,false,false,false,false,false,false,false,false,false,false,false,false,false,false,false,false,false,false,false,false,false,false,false,false,false,false,false,false,false,false,false,false,false,false,false,false,false,false,false,false,false,false,false,false,false,false,false,false,false,false,false,false,false,false,false,false,false,false,false,false,false,false,false,false,false,false,false,false,false,false,false,false,false,false,false,false,false,false,false,false,false,false,false,false,false,false,false,false,false,false,false,false,false,false,false,false,false,false,false,false,false,false,false,false,false,false,false,false,false,false,false,false,false,false,false,false,false,false,false,false,false,false,false,false,false,false,false,false,false,false,false,false,false,false,false,false,false,false,false,false,false,false,false,false,false,false,false,false,false,false,false,false,false,false,false,false,false,false,false,false,false,false,false,false,false,false,false,false,false,false,false,false,false,false,false,false,false,false,false,false,false,false,false,false,false,false,false,false,false,false,false,false,false,false,false,false,false,false,false,false,false,false,false,false,false,false,false,false,false,false,false,false,false,false,false,false,false,false,false,false,false,false,false,false,false,false,false,false,false,false,false,false,false,false,false,false,false,false,false,false,false,false,false,false,false,false,false,false,false,false,false,false,false,false,false,false,false,false,false,false,false,false,false,false,false,false,false,false,false,false,false,false,false,false,false,false,false,false,false,false,false,false,false,false,false,false,false,false,false,false,false,false,false,false,false,false,false,false,false,false,false,false,false,false,false,false,false,false,false,false,false,false,false,false,false,false,false,false,false,false,false,false,false,false,false,false,false,false,false,false,false,false,false,false,false,false,false,false,false,false,false,false,false,false,false,false,false,false,false,false,false,false,false,false,false,false,false,false,false,false,false,false,false,false,false,false,false,false,false,false,false,false,false,false,false,false,false,false,false,false,false,false,false,false,false,false,false,false,false,false,false,false,false,false,false,false,false,false,false,false,false,false,false,false,false,false,false,false,false,false,false,false,false,false,false,false,false,false,false,false,false,false,false,false,false,false,false,false,false,false,false,false,false,false,false,false,false,false,false,false,false,false,false,false,false,false,false,false,false,false,false,false,false,false,false,false,false,false,false,false,false,false,false,false,false,false,false,false,false,false,false,false,false,false,false,false,false,false,false,false,false,false,false,false,false,false,false,false,false,false,false,false,false,false,false,false,false,false,false,false,false,false,false,false,false,false,false,false,false,false,false,false,false,false,false,false,false,false,false,false,false,false,false,false,false,false,false,false,false,false,false,false,false,false,false,false,false,false,false,false,false,false,false,false,false,false,false,false,false,false,false,false,false,false,false,false,false,false,false,false,false,false,false,false,false,false,false,false,false,false,false,false,false,false,false,false,false,false,false,false,false,false,false,false,false,false,false,false,false,false,false,false,false,false,false,false,false,false,false,false,false,false,false,false,false,false,false,false,false,false,false,false,false,false,false,false,false,false,false,false,false,false,false,false,false,false,false,false,false,false,false,false,false,false,false,false,false,false,false,false,false,false,false,false,false,false,false,false,false,false,false,false,false,false,false,false,false,false,false,false,false,false,false,false,false,false,false,false,false,false,false,false,false,false,false,false,false,false,false,false,false,false,false,false,false,false,false,false,false,false,false,false,false,false,false,false,false,false,false,false,false,false,false,false,false,false,false,false,false,false,false,false,false,false,false,false,false,false,false,false,false,false,false,false,false,false,false,false,false,false,false,false,false,false,false,false,false,false,false,false,false,false,false,false,false,false,false,false,false,false,false,false,false,false,false,false,false,false,false,false,false,false,false,false,false,false,false,false,false,false,false,false,false,false,false,false,false,false,false,false,false,false,false,false,false,false,false,false,false,false,false,false,false,false,false,false,false,false,false,false,false,false,false,false,false,false,false,false,false,false,false,false,false,false,false,false,false,false,false,false,false,false,false,false,false,false,false,false,false,false,false,false,false,false,false,false,false,false,false,false,false,false,false,false,false,false,false,false,false,false,false,false,false,false,false,false,false,false,false,false,false,false,false,false,false,false,false,false,false,false,false,false,false,false,false,false,false,false,false,false,false,false,false,false,false,false,false,false,false,false,false,false,false,false,false,false,false,false,false,false,false,false,false,false,false,false,false,false,false,false,false,false,false,false,false,false,false,false,false,false,false,false,false,false,false,false,false,false,false,false,false,false,false,false,false,false,false,false,false,false,false,false,false,false,false,false,false,false,false,false,false,false,false,false,false,false,false,false,false,false,false,false,false,false,false,false,false,false,false,false,false,false,false,false,false,false,false,false,false,false,false,false,false,false,false,false,false,false,false,false,false,false,false,false,false,false,false,false,false,false,false,false,false,false,false,false,false,false,false,false,false,false,false,false,false,false,false,false,false,false,false,false,false,false,false,false,false,false,false,false,false,false,false,false,false,false,false,false,false,false,false,false,false,false,false,false,false,false,false,false,false,false,false,false,false,false,false,false,false,false,false,false,false,false,false,false,false,false,false,false,false,false,false,false,false,false,false,false,false,false,true,true,true,true,true,true,true,false,false,false,false,false,false,false,false,false,false,false,false,false,false,false,false,false,false,false,false,false,false,false,false,false,false,false,false,false,false,false,false,false,false,false,false,false,false,false,false,false,false,false,false,false,false,false,false,false,false,false,false,false,false,false,false,false,false,false,false,false,false,false,false,false,false,false,false,false,false,false,false,true,true,true,true,true,true,true,true,true,true,false,false,false,false,false,false,false,false,false,false,false,false,false,false,false,false,false,false,false,false,false,false,false,false,false,false,false,false,false,false,false,false,false,false,false,false,false,false,false,false,false,false,false,false,false,false,false,false,false,false,false,false,false,false,false,false,false,false,false,false,false,false,false,false,false,false,false,false,false,false,true,true,true,true,true,true,true,true,true,true,true,false,false,false,false,false,false,false,false,false,false,false,false,false,false,false,false,false,false,false,false,false,false,false,false,false,false,false,false,false,false,false,false,false,false,false,false,false,false,false,false,false,false,false,false,false,false,false,false,false,false,false,false,false,false,false,false,false,false,false,false,false,false,false,false,false,false,false,false,false,true,true,true,true,true,true,true,true,true,true,true,false,false,false,false,false,false,false,false,false,false,false,false,false,false,false,false,false,false,false,false,false,false,false,false,false,false,false,false,false,false,false,false,false,false,false,false,false,false,false,false,false,false,false,false,false,false,false,false,false,false,false,false,false,false,false,false,false,false,false,false,false,false,false,false,false,false,false,false,false,true,true,true,true,true,true,true,true,true,true,true,false,false,false,false,false,false,false,false,false,false,false,false,false,false,false,false,false,false,false,false,false,false,false,false,false,false,false,false,false,false,false,false,false,false,false,false,false,false,false,false,false,false,false,false,false,false,false,false,false,false,false,false,false,false,false,false,false,false,false,false,false,false,false,false,false,false,false,false,false,true,true,true,true,true,true,true,true,true,true,true,false,false,false,false,false,false,false,false,false,false,false,false,false,false,false,false,false,false,false,false,false,false,false,false,false,false,false,false,false,false,false,false,false,false,false,false,false,false,false,false,false,false,false,false,false,false,false,false,false,false,false,false,false,false,false,false,false,false,false,false,false,false,false,false,false,false,false,false,false,true,true,true,true,true,true,true,true,true,true,true,false,false,false,false,false,false,false,false,false,false,false,false,false,false,false,false,false,false,false,false,false,false,false,false,false,false,false,false,false,false,false,false,false,false,false,false,false,false,false,false,false,false,false,false,false,false,false,false,false,false,false,false,false,false,false,false,false,false,false,false,false,false,false,false,false,false,false,false,false,true,true,true,true,true,true,true,true,true,true,true,false,false,false,false,false,false,false,false,false,false,false,false,false,false,false,false,false,false,false,false,false,false,false,false,false,false,false,false,false,false,false,false,false,false,false,false,false,false,false,false,false,false,false,false,false,false,false,false,false,false,false,false,false,false,false,false,false,false,false,false,false,false,false,false,false,false,false,false,false,true,true,true,true,true,true,true,true,true,true,true,false,false,false,false,false,false,false,false,false,false,false,false,false,false,false,false,false,false,false,false,false,false,false,false,false,false,false,false,false,false,false,false,false,false,false,false,false,false,false,false,false,false,false,false,false,false,false,false,false,false,false,false,false,false,false,false,false,false,false,false,false,false,false,false,false,false,false,false,false,true,true,true,true,true,true,true,true,true,true,true,false,false,false,false,false,false,false,false,false,false,false,false,false,false,false,false,false,false,false,false,false,false,false,false,false,false,false,false,false,false,false,false,false,false,false,false,false,false,false,false,false,false,false,false,false,false,false,false,false,false,false,false,false,false,false,false,false,false,false,false,false,false,false,false,false,false,false,false,false,false,false,false,false,false,false,false,false,false,false,false,false,false,false,false,false,false,false,false,false,false,false,false,false,false,false,false,false,false,false,false,false,false,false,false,false,false,false,false,false,false,false,false,false,false,false,false,false,false,false,false,false,false,false,false,false,false,false,false,false,false,false,false,false,false,false,false,false,false,false,false,false,false,false,false,false,false,false,false,false,false,false,false,false,false,false,false,false,false,false,false,false,false,false,false,false,false,false,false,false,false,false,false,false,false,false,false,false,false,false,false,false,false,false,false,false,false,false,false,false,false,false,false,false,false,false,false,false,false,false,false,false,false,false,false,false,false,false,false,false,false,false,false,false,false,false,false,false,false,false,false,false,false,false,false,false,false,false,false,false,false,false,false,false,false,false,false,false,false,false,false,false,false,false,false,false,false,false,false,false,false,false,false,false,false,false,false,false,false,false,false,false,false,false,false,false,false,false,false,false,false,false,false,false,false,false,false,false,false,false,false,false,false,false,false,false,false,false,false,false,false,false,false,false,false,false,false,false,false,false,false,false,false,false,false,false,false,false,false,false,false,false,false,false,false,false,false,false,false,false,false,false,false,false,false,false,false,false,false,false,false,false,false,false,false,false,false,false,false,false,false,false,false,false,false,false,false,false,false,false,false,false,false,false,false,false,false,false,false,false,false,false,false,false,false,false,false,false,false,false,false,false,false,false,false,false,false,false,false,false,false,false,false,false,false,false,false,false,false,false,false,false,false,false,false,false,false,false,false,false,false,false,false,false,false,false,false,false,false,false,false,false,false,false,false,false,false,false,false,false,false,false,false,false,false,false,false,false,false,false,false,false,false,false,false,false,false,false,false,false,false,false,false,false,false,false,false,false,false,false,false,false,false,false,false,false,false,false,false,false,false,false,false,false,false,false,false,false,false,false,false,false,false,false,false,false,false,false,false,false,false,false,false,false,false,false,false,false,false,false,false],"blocked":[true,true,true,true,true,true,true,true,true,true,true,true,true,true,true,true,true,true,true,true,true,true,true,true,true,true,true,true,true,true,true,true,true,true,true,true,true,true,true,true,true,true,true,true,true,true,true,true,true,true,true,true,true,true,true,true,true,true,true,true,true,true,true,true,true,true,true,true,true,true,true,true,true,true,true,true,true,true,true,true,true,true,true,true,true,true,true,true,true,true,true,true,true,true,true,true,true,true,true,true,true,true,true,true,true,true,true,true,true,true,true,true,true,true,true,true,true,true,true,true,true,true,true,true,true,true,true,true,true,true,true,true,true,true,true,true,true,true,true,true,true,true,true,true,true,true,true,true,true,true,true,true,true,true,true,true,true,true,true,true,true,true,true,true,true,true,true,true,true,true,true,false,false,false,false,false,false,true,true,true,true,true,true,true,true,true,true,true,true,true,true,true,true,true,true,true,true,true,true,true,true,true,true,true,true,true,true,true,true,true,true,true,true,true,true,true,true,true,true,true,true,true,true,true,true,true,true,true,true,true,true,true,true,true,true,true,true,true,true,true,true,true,true,true,true,true,true,true,true,true,true,false,false,false,false,false,false,true,true,true,true,true,true,true,true,true,true,true,true,true,true,true,true,true,true,true,true,true,true,true,false,false,false,false,false,false,false,false,false,true,true,true,true,true,true,true,true,true,true,true,true,true,true,true,true,true,true,true,true,true,true,true,true,true,true,true,true,true,true,true,true,true,true,true,true,true,true,true,true,true,true,false,false,false,false,false,false,true,true,true,true,true,true,true,true,true,true,true,true,true,true,true,true,true,true,true,true,true,true,true,false,false,false,false,false,false,false,false,false,true,true,true,true,true,true,true,true,true,true,true,true,true,true,true,true,true,true,true,true,true,true,true,true,true,true,true,true,true,true,true,true,true,true,true,true,true,true,true,true,true,true,false,false,false,false,false,false,true,true,true,true,true,true,true,true,true,true,true,true,true,true,true,true,true,true,true,true,true,true,true,false,false,false,false,false,false,false,false,false,true,true,true,true,true,true,true,true,true,true,true,true,true,true,true,false,false,false,false,false,false,true,true,true,true,true,true,true,true,true,true,true,true,true,true,true,true,true,true,true,true,true,false,false,false,false,false,false,true,true,true,true,true,true,true,true,true,true,true,true,true,true,true,true,true,true,true,true,true,true,true,false,false,false,false,false,false,false,false,false,true,true,true,true,true,true,true,true,true,true,true,true,true,true,true,false,false,false,false,false,false,true,true,true,true,true,true,true,true,true,true,true,true,true,true,true,true,true,true,true,true,true,false,false,false,false,false,false,true,true,false,false,false,false,false,false,false,false,false,false,false,false,false,false,false,false,false,false,false,false,false,false,false,false,false,false,false,false,false,false,false,false,false,false,false,false,false,false,false,false,false,false,false,false,false,false,false,false,false,false,false,true,true,true,true,true,true,true,true,true,true,true,true,true,true,true,true,true,true,true,true,true,false,false,false,false,false,false,true,true,false,true,true,true,true,true,true,true,true,true,true,true,true,true,true,true,true,true,true,true,true,false,false,false,false,false,false,false,false,false,true,true,true,true,true,true,true,true,true,true,true,true,true,true,false,false,false,false,false,false,false,true,true,true,true,true,true,true,true,true,true,true,true,true,true,true,true,true,true,true,true,true,false,false,false,false,false,false,true,true,false,true,true,true,true,true,true,true,true,true,true,true,true,true,true,true,true,true,true,true,true,true,true,true,false,true,true,true,true,true,true,true,true,true,true,true,true,true,true,true,true,true,true,true,false,false,false,false,false,false,false,true,true,true,true,true,true,true,true,true,true,true,true,true,true,true,true,true,true,true,true,true,true,true,true,true,false,true,true,true,false,true,true,true,true,true,true,true,true,true,true,true,true,true,true,true,true,true,true,true,true,true,true,true,false,true,true,true,true,true,true,true,true,true,true,true,true,true,true,true,true,true,true,true,false,false,false,false,false,false,false,true,true,true,true,true,true,true,true,true,true,true,true,true,true,true,true,true,true,true,true,true,true,true,true,true,false,true,true,true,false,true,true,true,true,true,true,true,true,true,true,true,true,true,true,true,true,true,true,true,true,true,true,true,false,true,true,true,true,true,true,true,true,true,true,true,true,true,true,true,true,true,true,true,false,true,true,true,true,true,true,true,true,true,true,true,true,true,true,true,true,true,true,true,true,true,true,true,true,true,true,true,true,true,true,true,false,true,true,true,false,true,true,true,true,true,true,true,true,true,true,true,true,true,true,true,true,true,true,true,true,true,true,true,false,true,true,true,true,true,true,true,true,true,true,true,true,true,true,true,true,true,true,false,false,false,false,false,false,false,false,false,true,true,true,true,true,true,true,true,true,true,true,true,true,true,true,true,true,true,true,true,true,true,true,true,false,true,true,true,false,true,true,true,true,true,true,true,true,true,true,true,true,true,true,true,true,true,true,true,true,true,true,true,false,true,true,true,true,true,true,true,true,true,true,true,true,true,true,true,true,true,true,false,false,false,false,false,false,false,false,false,true,true,true,true,true,true,true,true,true,true,true,true,true,true,true,true,true,true,true,true,true,true,true,true,false,true,true,true,false,true,true,true,true,true,true,false,false,false,false,false,false,false,false,false,false,false,false,false,false,false,false,false,false,false,false,false,false,false,false,false,false,false,false,false,false,false,false,false,false,false,false,false,false,false,false,false,false,false,false,false,true,true,true,true,true,true,true,true,true,true,true,true,true,true,true,true,true,true,true,true,true,true,true,true,false,true,true,true,false,true,true,true,true,true,true,false,true,true,true,true,true,true,true,true,true,true,true,true,true,true,true,true,false,true,true,true,true,true,true,true,true,true,true,true,true,true,true,true,true,true,true,false,false,false,false,false,false,false,false,false,true,true,true,true,true,true,true,true,true,true,true,true,true,true,true,true,true,true,true,true,true,true,true,true,false,true,true,true,false,true,true,true,true,true,true,false,true,true,true,true,true,true,true,true,true,true,true,true,true,true,true,true,false,true,true,true,true,true,true,true,true,true,true,true,true,true,true,true,true,true,true,false,false,false,false,false,false,false,false,false,true,true,true,true,true,true,true,true,true,true,true,true,true,true,true,true,true,true,true,true,true,true,true,true,false,true,true,true,false,true,true,true,true,true,true,false,true,true,true,true,true,true,true,true,true,true,true,true,true,true,true,true,false,true,true,true,true,true,true,true,true,true,true,true,true,true,true,true,true,true,true,false,false,false,false,false,false,false,false,false,true,true,true,true,true,true,true,true,true,true,true,true,true,true,true,true,true,true,true,true,true,true,true,true,false,true,true,true,false,true,true,true,true,true,true,false,true,true,true,true,true,true,true,true,true,true,true,true,true,true,true,true,false,true,true,true,true,true,true,true,true,true,true,true,true,true,true,true,true,true,true,true,false,true,true,true,true,true,true,true,true,true,true,true,true,true,true,true,true,true,true,true,true,true,true,true,true,true,true,true,true,true,true,true,false,true,true,true,false,true,true,true,true,true,true,false,true,true,true,true,true,true,true,true,true,true,true,true,true,true,true,false,false,false,false,false,false,false,false,true,true,true,true,true,true,true,true,true,true,true,true,true,false,true,true,true,true,true,true,true,true,true,true,true,true,true,true,true,true,true,true,true,true,true,true,true,true,true,true,true,true,true,true,true,false,false,false,false,false,false,false,false,false,true,true,false,true,true,true,true,true,true,true,true,true,true,true,true,true,true,true,false,false,false,false,false,false,false,false,true,true,true,true,true,true,true,true,true,true,true,true,true,false,true,true,true,true,true,true,true,true,true,true,true,true,true,true,true,true,true,true,true,true,true,true,false,false,false,false,false,false,true,true,true,false,false,false,false,false,false,false,false,false,true,true,false,true,true,true,true,true,true,true,true,true,true,true,true,true,true,true,false,false,false,false,false,false,false,false,true,true,true,true,true,true,true,true,true,true,true,true,true,false,true,true,true,true,true,true,true,true,true,true,true,true,true,true,true,true,true,true,true,true,true,true,false,false,false,false,false,false,true,true,true,false,false,false,false,false,false,false,false,false,false,false,false,false,false,false,false,false,false,false,false,false,false,false,false,false,false,false,false,false,false,false,false,false,false,false,false,false,false,false,false,false,false,false,false,false,false,false,false,false,true,true,true,true,true,true,true,true,true,true,true,true,true,true,true,true,true,true,true,true,true,true,false,false,false,false,false,false,false,false,false,false,false,false,false,false,false,false,false,false,false,false,false,false,false,false,false,false,false,false,false,false,false,false,false,false,false,false,false,false,false,false,false,false,false,false,true,true,false,true,true,true,true,true,true,true,true,true,true,false,true,true,true,true,true,true,true,true,true,true,true,true,true,true,true,true,true,true,true,true,true,true,false,false,false,false,false,false,true,true,true,false,false,false,false,false,false,false,false,false,true,true,false,true,true,true,true,true,true,true,true,true,true,true,true,true,true,true,false,false,false,false,false,false,false,false,true,true,false,true,true,true,true,true,true,true,true,true,true,false,true,true,true,true,true,true,true,true,true,true,true,true,true,true,true,true,true,true,true,true,true,true,false,false,false,false,false,false,true,true,true,false,false,false,false,false,false,false,false,false,true,true,false,true,true,true,true,true,true,true,true,true,true,true,true,true,true,true,false,false,false,false,false,false,false,false,true,true,false,true,true,true,true,true,true,true,true,true,true,false,true,true,true,true,true,true,true,true,true,true,true,true,true,true,true,true,true,true,true,true,true,true,false,false,false,false,false,false,true,true,true,false,false,false,false,false,false,false,false,false,true,true,false,true,true,true,true,true,true,true,true,true,true,true,true,true,true,true,false,false,false,false,false,false,false,false,true,true,false,true,true,true,true,true,true,true,true,true,true,false,true,true,true,true,true,true,true,true,true,true,true,true,true,true,true,true,true,true,true,true,true,true,false,false,false,false,false,false,true,true,true,false,true,true,true,true,true,true,true,true,true,true,false,true,true,true,true,true,true,true,true,true,true,true,true,true,true,true,false,false,false,false,false,false,false,false,true,true,false,true,true,true,true,true,true,true,false,false,false,false,false,false,false,false,false,true,true,true,true,true,true,true,true,true,true,true,true,true,true,true,true,true,true,true,true,true,true,true,true,true,true,false,true,true,true,true,true,true,true,true,true,true,false,true,true,true,true,true,true,true,true,true,true,true,true,true,true,true,true,false,true,true,true,true,true,true,true,true,false,true,true,true,true,true,true,true,false,false,false,false,false,false,false,false,false,true,true,true,true,true,true,true,true,true,true,true,true,true,true,true,true,true,true,true,true,true,true,true,false,false,false,false,false,false,false,false,false,true,true,true,true,true,false,true,true,true,true,true,true,true,true,true,true,true,true,true,true,true,true,false,true,true,true,true,true,false,false,false,false,false,false,false,false,false,true,true,false,false,false,false,false,false,false,false,false,true,true,true,true,true,true,true,true,true,true,true,true,true,true,true,true,true,true,true,true,true,true,true,false,false,false,false,false,false,false,false,false,true,true,true,true,true,false,true,true,true,true,true,true,true,true,true,true,true,true,true,false,false,false,false,false,false,false,false,true,false,false,false,false,false,false,false,false,false,true,true,false,false,false,false,false,false,false,false,false,true,true,true,true,true,true,true,true,true,true,true,true,true,true,true,true,true,true,true,true,true,true,true,false,false,false,false,false,false,false,false,false,true,true,true,true,true,false,true,true,true,true,true,true,true,true,true,true,true,true,true,false,false,false,false,false,false,false,false,true,false,false,false,false,false,false,false,false,false,true,true,false,false,false,false,false,false,false,false,false,true,true,true,true,true,true,true,true,true,true,true,true,true,true,true,true,true,true,true,true,true,true,true,false,false,false,false,false,false,false,false,false,false,false,false,false,false,false,false,false,false,false,false,false,false,false,false,false,false,false,false,false,false,false,false,false,false,false,false,false,false,false,false,false,false,false,false,false,false,true,true,false,false,false,false,false,false,false,false,false,true,true,true,true,true,true,true,true,true,true,true,true,true,true,true,true,true,true,true,true,true,true,true,false,false,false,false,false,false,false,false,false,true,true,false,false,false,false,false,false,false,false,false,true,true,true,true,true,true,true,true,false,false,false,false,false,false,false,false,true,false,false,false,false,false,false,false,false,false,true,true,false,false,false,false,false,false,false,false,false,true,true,true,true,true,true,true,true,true,true,true,true,true,true,true,true,true,true,true,true,true,true,true,false,false,false,false,false,false,false,false,false,true,true,false,false,false,false,false,false,false,false,false,true,true,true,true,true,true,true,true,false,false,false,false,false,false,false,false,true,false,false,false,false,false,false,false,false,false,true,true,false,false,false,false,false,false,false,false,false,true,true,true,true,true,true,true,true,true,true,true,true,true,true,true,true,true,true,true,true,true,true,true,true,true,true,true,true,true,true,true,true,true,true,false,false,false,false,false,false,false,false,false,true,true,true,true,true,true,true,true,false,false,false,false,false,false,false,false,true,false,false,false,false,false,false,false,false,false,true,true,false,false,false,false,false,false,false,false,false,true,true,true,true,true,true,true,true,true,true,true,true,true,true,true,true,true,true,true,true,true,true,true,true,true,true,true,true,true,true,true,true,true,true,false,false,false,false,false,false,false,false,false,true,true,true,true,true,true,true,true,false,false,false,false,false,false,false,false,true,false,false,false,false,false,false,false,false,false,true,true,true,true,true,true,true,true,true,true,true,true,true,true,true,true,true,true,true,true,true,true,true,true,true,true,true,true,true,true,true,true,true,true,true,true,true,true,true,true,true,true,true,true,true,false,false,false,false,false,false,false,false,false,true,true,true,true,true,true,true,true,true,true,true,true,true,true,true,true,true,false,false,false,false,false,false,false,false,false,true,true,true,true,true,true,true,true,true,true,true,true,true,true,true,true,true,true,true,true,true,true,true,true,true,true,true,true,true,true,true,true,true,true,true,true,true,true,true,true,true,true,true,true,true,false,false,false,false,false,false,false,false,false,true,true,true,true,true,true,true,true,true,true,true,true,true,true,true,true,true,true,true,true,true,true,true,true,true,true,true,true,true,true,true,true,true,true,true,true,true,true,true,true,true,true,true,true,true,true,true,true,true,true,true,true,true,true,true,true,true,true,true,true,true,true,true,true,true,true,true,true,true,true,true,false,false,false,false,false,false,false,false,false,true,true,true,true,true,true,true,true,true,true,true,true,true,true,true,true,true,true,true,true,true,true,true,true,true,true,true,true,true,true,true,true,true,true,true,true,true,true,true,true,true,true,true,true,true,true,true,true,true,true,true,true,true,true,true,true,true,true,true,true,true,true,true,true,true,true,true,true,true,true,true,false,false,false,false,false,false,false,false,false,true,true,true,true,true,true,true,true,true,true,true,true,true,true,true,true,true,true,true,true,true,true,true,true,true,true,true,true,true,true,true,true,true,true,true,true,true,true,true,true,true,true,true,true,true,true,true,true,true,true,true,true,true,true,true,true,true,true,true,true,true,true,true,true,true,true,true,true,true,true,true,false,false,false,false,false,false,false,false,false,true,true,true,true,true,true,true,true,true,true,true,true,true,true,true,true,true,true,true,true,true,true,true,true,true,true,true,true,true,true,true,true,true,true,true,true,true,true,true,true,true,true,true,true,true,true,true,true,true,true,true,true,true,true,true,true,true,true,true,true,true,true,true,true,true,true,true,true,true,true,true,true,true,true,true,true,true,true,true,true,true,true,true,true,true,true,true,true,true,true,true,true,true,true,true,true,true,true,true,true,true,true,true,true,true,true,true,true,true,true,true,true,true,true,true,true,true,true,true,true,true,true,true,true,true,true,true,true],"depth":1}}]}][{"marker":[0],"components":[null]},{"marker":[1],"components":[null]},{"marker":[2],"components":[null]},{"marker":[3],"components":[null]},{"marker":[5],"components":[null]}][{"marker":[0],"components":[null]},{"marker":[1],"components":[null]},{"marker":[2],"components":[null]},{"marker":[3],"components":[null]},{"marker":[5],"components":[null]}][{"marker":[0],"components":[null]},{"marker":[1],"components":[null]},{"marker":[2],"components":[null]},{"marker":[3],"components":[null]},{"marker":[5],"components":[null]}][{"marker":[0],"components":[null]},{"marker":[1],"components":[null]},{"marker":[2],"components":[null]},{"marker":[3],"components":[null]},{"marker":[5],"components":[null]}]